idsecure_cli/__init__.py
idsecure_cli/client.py
idsecure_cli/main.py
idsecure_cli-0.1.2.dist-info/METADATA
idsecure_cli-0.1.2.dist-info/WHEEL
idsecure_cli-0.1.2.dist-info/entry_points.txt
idsecure_cli-0.1.2.dist-info/top_level.txt
idsecure_cli-0.1.2.dist-info/RECORD
