Metadata-Version: 2.4
Name: idsecure-cli
Version: 0.1.2
Summary: Python SDK and CLI tool for the IDSecure API
Author: Tulio Amancio
Project-URL: Homepage, https://github.com/tsuriu/idsecure-cli
Project-URL: Bug Tracker, https://github.com/tsuriu/idsecure-cli/issues
Keywords: idsecure,sdk,api,client
Classifier: Programming Language :: Python :: 3
Classifier: License :: OSI Approved :: MIT License
Classifier: Operating System :: OS Independent
Requires-Python: >=3.8
Requires-Dist: httpx>=0.24.0
Requires-Dist: click>=8.1.0
Requires-Dist: loguru>=0.7.0
